{
  "render_statistics": [],
  "build_statistics": [
    {
      "frame_index": 0,
      "sah": 178.79549,
      "epo": 390.0261
    },
    {
      "frame_index": 1,
      "sah": 172.55392,
      "epo": 384.79962
    },
    {
      "frame_index": 2,
      "sah": 169.14474,
      "epo": 376.2244
    },
    {
      "frame_index": 3,
      "sah": 166.64351,
      "epo": 347.81723
    },
    {
      "frame_index": 4,
      "sah": 160.99725,
      "epo": 344.52875
    },
    {
      "frame_index": 5,
      "sah": 160.43636,
      "epo": 346.0144
    },
    {
      "frame_index": 6,
      "sah": 158.2206,
      "epo": 348.2407
    },
    {
      "frame_index": 7,
      "sah": 155.52235,
      "epo": 342.4559
    },
    {
      "frame_index": 8,
      "sah": 152.79898,
      "epo": 334.13153
    },
    {
      "frame_index": 9,
      "sah": 155.65068,
      "epo": 362.88025
    },
    {
      "frame_index": 10,
      "sah": 154.93965,
      "epo": 354.31247
    },
    {
      "frame_index": 11,
      "sah": 163.35603,
      "epo": 373.91504
    },
    {
      "frame_index": 12,
      "sah": 151.31277,
      "epo": 377.79822
    },
    {
      "frame_index": 13,
      "sah": 155.2346,
      "epo": 387.27716
    },
    {
      "frame_index": 14,
      "sah": 154.55666,
      "epo": 378.1915
    },
    {
      "frame_index": 15,
      "sah": 154.56157,
      "epo": 380.48703
    },
    {
      "frame_index": 16,
      "sah": 148.52,
      "epo": 365.6506
    },
    {
      "frame_index": 17,
      "sah": 149.05455,
      "epo": 365.5731
    },
    {
      "frame_index": 18,
      "sah": 152.48715,
      "epo": 371.31448
    },
    {
      "frame_index": 19,
      "sah": 151.05214,
      "epo": 367.10233
    },
    {
      "frame_index": 20,
      "sah": 156.38261,
      "epo": 377.53497
    },
    {
      "frame_index": 21,
      "sah": 156.17201,
      "epo": 378.61304
    },
    {
      "frame_index": 22,
      "sah": 159.09924,
      "epo": 377.17963
    },
    {
      "frame_index": 23,
      "sah": 158.70596,
      "epo": 381.1438
    },
    {
      "frame_index": 24,
      "sah": 158.93567,
      "epo": 376.1667
    },
    {
      "frame_index": 25,
      "sah": 158.662,
      "epo": 368.4515
    },
    {
      "frame_index": 26,
      "sah": 164.01164,
      "epo": 358.51843
    },
    {
      "frame_index": 27,
      "sah": 167.51994,
      "epo": 362.46863
    },
    {
      "frame_index": 28,
      "sah": 161.50642,
      "epo": 344.10846
    },
    {
      "frame_index": 29,
      "sah": 154.36906,
      "epo": 353.8318
    },
    {
      "frame_index": 30,
      "sah": 158.39183,
      "epo": 359.06714
    },
    {
      "frame_index": 31,
      "sah": 165.81665,
      "epo": 358.41876
    },
    {
      "frame_index": 32,
      "sah": 162.3889,
      "epo": 362.4929
    },
    {
      "frame_index": 33,
      "sah": 165.81451,
      "epo": 363.29034
    },
    {
      "frame_index": 34,
      "sah": 170.21922,
      "epo": 370.1659
    },
    {
      "frame_index": 35,
      "sah": 159.98888,
      "epo": 376.3375
    },
    {
      "frame_index": 36,
      "sah": 159.32103,
      "epo": 374.9984
    },
    {
      "frame_index": 37,
      "sah": 157.64252,
      "epo": 374.92874
    },
    {
      "frame_index": 38,
      "sah": 160.57086,
      "epo": 392.4592
    },
    {
      "frame_index": 39,
      "sah": 160.21432,
      "epo": 393.64832
    },
    {
      "frame_index": 40,
      "sah": 167.12967,
      "epo": 384.8266
    },
    {
      "frame_index": 41,
      "sah": 169.59592,
      "epo": 381.52216
    },
    {
      "frame_index": 42,
      "sah": 169.78372,
      "epo": 381.76465
    },
    {
      "frame_index": 43,
      "sah": 166.0873,
      "epo": 376.11548
    },
    {
      "frame_index": 44,
      "sah": 173.18669,
      "epo": 380.17236
    },
    {
      "frame_index": 45,
      "sah": 190.69322,
      "epo": 401.00226
    },
    {
      "frame_index": 46,
      "sah": 184.43674,
      "epo": 394.80908
    },
    {
      "frame_index": 47,
      "sah": 181.99329,
      "epo": 399.0706
    },
    {
      "frame_index": 48,
      "sah": 176.49991,
      "epo": 369.8221
    },
    {
      "frame_index": 49,
      "sah": 185.96996,
      "epo": 384.63483
    },
    {
      "frame_index": 50,
      "sah": 185.14856,
      "epo": 390.85703
    },
    {
      "frame_index": 51,
      "sah": 184.5115,
      "epo": 366.16452
    },
    {
      "frame_index": 52,
      "sah": 178.5582,
      "epo": 361.97644
    },
    {
      "frame_index": 53,
      "sah": 178.36366,
      "epo": 361.6952
    },
    {
      "frame_index": 54,
      "sah": 157.31613,
      "epo": 346.69888
    },
    {
      "frame_index": 55,
      "sah": 158.90846,
      "epo": 344.94116
    },
    {
      "frame_index": 56,
      "sah": 167.55801,
      "epo": 348.44135
    },
    {
      "frame_index": 57,
      "sah": 265.2151,
      "epo": 390.90463
    },
    {
      "frame_index": 58,
      "sah": 173.95688,
      "epo": 375.18787
    },
    {
      "frame_index": 59,
      "sah": 166.58984,
      "epo": 353.5828
    },
    {
      "frame_index": 60,
      "sah": 162.75871,
      "epo": 348.82654
    },
    {
      "frame_index": 61,
      "sah": 167.0078,
      "epo": 350.3334
    },
    {
      "frame_index": 62,
      "sah": 161.07976,
      "epo": 346.81427
    },
    {
      "frame_index": 63,
      "sah": 156.8037,
      "epo": 343.2848
    },
    {
      "frame_index": 64,
      "sah": 158.88535,
      "epo": 348.6494
    },
    {
      "frame_index": 65,
      "sah": 152.64726,
      "epo": 334.0011
    },
    {
      "frame_index": 66,
      "sah": 147.0967,
      "epo": 313.39053
    },
    {
      "frame_index": 67,
      "sah": 147.01079,
      "epo": 317.92413
    },
    {
      "frame_index": 68,
      "sah": 146.88138,
      "epo": 319.9185
    },
    {
      "frame_index": 69,
      "sah": 148.32043,
      "epo": 319.89624
    },
    {
      "frame_index": 70,
      "sah": 149.0926,
      "epo": 320.84775
    },
    {
      "frame_index": 71,
      "sah": 149.50543,
      "epo": 323.3255
    },
    {
      "frame_index": 72,
      "sah": 146.70702,
      "epo": 316.61508
    },
    {
      "frame_index": 73,
      "sah": 146.75893,
      "epo": 320.66974
    },
    {
      "frame_index": 74,
      "sah": 146.04156,
      "epo": 316.56003
    },
    {
      "frame_index": 75,
      "sah": 146.36389,
      "epo": 317.9507
    },
    {
      "frame_index": 76,
      "sah": 146.2763,
      "epo": 317.79083
    },
    {
      "frame_index": 77,
      "sah": 150.68861,
      "epo": 330.38812
    },
    {
      "frame_index": 78,
      "sah": 152.74727,
      "epo": 328.0044
    },
    {
      "frame_index": 79,
      "sah": 150.65028,
      "epo": 318.87787
    },
    {
      "frame_index": 80,
      "sah": 150.7366,
      "epo": 318.74527
    },
    {
      "frame_index": 81,
      "sah": 151.29315,
      "epo": 324.83627
    },
    {
      "frame_index": 82,
      "sah": 150.64992,
      "epo": 322.17172
    },
    {
      "frame_index": 83,
      "sah": 154.82436,
      "epo": 330.13037
    },
    {
      "frame_index": 84,
      "sah": 159.04942,
      "epo": 333.33844
    },
    {
      "frame_index": 85,
      "sah": 159.55188,
      "epo": 333.28723
    },
    {
      "frame_index": 86,
      "sah": 160.16148,
      "epo": 331.1305
    },
    {
      "frame_index": 87,
      "sah": 161.39304,
      "epo": 335.79187
    },
    {
      "frame_index": 88,
      "sah": 162.61778,
      "epo": 336.63287
    },
    {
      "frame_index": 89,
      "sah": 165.47495,
      "epo": 337.99512
    },
    {
      "frame_index": 90,
      "sah": 167.44356,
      "epo": 341.6925
    },
    {
      "frame_index": 91,
      "sah": 168.57042,
      "epo": 339.46585
    },
    {
      "frame_index": 92,
      "sah": 169.1077,
      "epo": 333.42676
    },
    {
      "frame_index": 93,
      "sah": 168.24736,
      "epo": 334.97946
    },
    {
      "frame_index": 94,
      "sah": 177.32239,
      "epo": 345.36084
    },
    {
      "frame_index": 95,
      "sah": 186.51405,
      "epo": 363.4552
    },
    {
      "frame_index": 96,
      "sah": 179.24646,
      "epo": 346.224
    },
    {
      "frame_index": 97,
      "sah": 186.75261,
      "epo": 361.5979
    },
    {
      "frame_index": 98,
      "sah": 182.76366,
      "epo": 358.16373
    },
    {
      "frame_index": 99,
      "sah": 196.41624,
      "epo": 370.95786
    },
    {
      "frame_index": 100,
      "sah": 200.74965,
      "epo": 372.37268
    },
    {
      "frame_index": 101,
      "sah": 188.56252,
      "epo": 364.16156
    },
    {
      "frame_index": 102,
      "sah": 207.85149,
      "epo": 375.27063
    },
    {
      "frame_index": 103,
      "sah": 206.37772,
      "epo": 383.07697
    },
    {
      "frame_index": 104,
      "sah": 238.77159,
      "epo": 388.14886
    },
    {
      "frame_index": 105,
      "sah": 233.46225,
      "epo": 412.23932
    },
    {
      "frame_index": 106,
      "sah": 250.92484,
      "epo": 410.39407
    }
  ]
}